setup.cfg
setup.py
open_exchange_rates/__init__.py
open_exchange_rates/client.py
open_exchange_rates/exceptions.py
open_exchange_rates/tests.py
open_exchange_rates.egg-info/PKG-INFO
open_exchange_rates.egg-info/SOURCES.txt
open_exchange_rates.egg-info/dependency_links.txt
open_exchange_rates.egg-info/not-zip-safe
open_exchange_rates.egg-info/requires.txt
open_exchange_rates.egg-info/top_level.txt