Metadata-Version: 1.1
Name: open-exchange-rates
Version: 1.0a1
Summary: An Open Exchange Rates python client
Home-page: https://github.com/danielterhorst/open_exchange_rates
Author: Daniel ter Horst
Author-email: mail@danielterhorst.nl
License: GNU General Public License v2 (GPLv2)
Platform: UNKNOWN
Classifier: Development Status :: 3 - Alpha
Classifier: Intended Audience :: Developers
Classifier: Topic :: Software Development :: Libraries :: Python Modules
Classifier: License :: OSI Approved :: GNU General Public License v2 (GPLv2)
Classifier: Programming Language :: Python :: 2
Classifier: Programming Language :: Python :: 2.7
